mcpstack_jupyter-0.0.4.dist-info/METADATA
mcpstack_jupyter-0.0.4.dist-info/WHEEL
mcpstack_jupyter-0.0.4.dist-info/entry_points.txt
mcpstack_jupyter-0.0.4.dist-info/licenses/LICENSE
mcpstack_jupyter/__init__.py
mcpstack_jupyter/tools/jupyter/__init__.py
mcpstack_jupyter/tools/jupyter/cli.py
mcpstack_jupyter/tools/jupyter/configuration/cli_defaults.yaml
mcpstack_jupyter/tools/jupyter/configuration/env_defaults.yaml
mcpstack_jupyter/tools/jupyter/configuration/tools.yaml
mcpstack_jupyter/tools/jupyter/jupyter.py
mcpstack_jupyter/tools/jupyter/utils/config_loader.py
mcpstack_jupyter-0.0.4.dist-info/RECORD
