Metadata-Version: 2.4
Name: mcpstack-jupyter
Version: 0.0.4
Summary: [MCP Tool] Jupyter, let the LLM perform Jupyter Notebook reproducible analysis — Derived from the official Jupyter MCP Server by @datalayer.tech
Keywords: mcp,mcpstack,mcpPipeline,tool,template
Author-Email: Provost Simon <s.g.provost@kent.ac.uk>
License-Expression: MIT
Requires-Python: >=3.10
Requires-Dist: typer>=0.9.0
Requires-Dist: beartype>=0.21.0
Requires-Dist: rich>=13.0.0
Requires-Dist: rich-argparse>=1.4.0
Requires-Dist: rich-pyfiglet>=1.0.0
Requires-Dist: click>=8.1.8
Requires-Dist: jupyter-mcp-server>=0.11.0
Requires-Dist: jupyterlab==4.4.1
Requires-Dist: jupyter-collaboration==3.1.2
Requires-Dist: ipykernel
Requires-Dist: datalayer_pycrdt==0.12.17
Requires-Dist: mcpstack>=0.0.2
Requires-Dist: pytest==7.4.3
Requires-Dist: pytest-asyncio>=0.23.8
